chatstats/__init__.py
chatstats/sync_api.py
chatstats-0.1.5.dist-info/WHEEL
chatstats-0.1.5.dist-info/METADATA
chatstats-0.1.5.dist-info/RECORD
