Metadata-Version: 2.1
Name: chatstats
Version: 0.1.5
Summary: python sdk for chat-stats.ru
Author: Bogdan
Author-email: evstrat.bg@gmail.com
Requires-Python: >=3.6,<4.0
Classifier: Programming Language :: Python :: 3
Classifier: Programming Language :: Python :: 3.6
Classifier: Programming Language :: Python :: 3.7
Classifier: Programming Language :: Python :: 3.8
Requires-Dist: requests (>=2.23.0,<3.0.0)
